{
  "objects": [
    {
      "name": "background",
      "position": "0, 0",
      "visible": true
    },
    {
      "name": "left",
      "position": "70, 160",
      "visible": true
    },
    {
      "name": "center",
      "position": "[center], 160",
      "visible": true
    },
    {
      "name": "right",
      "position": "1000, 160",
      "visible": true
    },
    {
      "name": "textbox",
      "position": "0, 520",
      "visible": true
    },
    {
      "name": "choice",
      "position": "50, [center]",
      "visible": false
    },
    {
      "name": "fps_text",
      "position": "0, 0",
      "font": "arial_tx",
      "color": "255, 255, 255, 255",
      "visible": true
    },
    {
      "name": "textbox_name",
      "position": "150, 480",
      "font": "arial",
      "color": "88, 166, 255, 255",
      "visible": true
    },
    {
      "name": "textbox_text",
      "position": "160, 540",
      "font": "arial_tx",
      "color": "255, 255, 255, 255",
      "visible": true
    }
  ]
}